Workbook

Sheet Dataset Overview
A1: Messy Sales Dataset - Data Cleaning & Analysis Challenge
A3: This dataset has been intentionally generated with real-world data quality issues to simulate raw business data.
A4: As a data analyst, your goal is to clean, validate, transform, and analyze this data.
A6: Issue Category | B6: Description | C6: Examples in Dataset | D6: Analytical Impact
A7: Duplicates | B7: Repeated transaction IDs with identical or conflicting records. | C7: Multiple rows with 'TXN-1012' | D7: Overstates revenue and volume metrics if unhandled.
A8: Date Inconsistencies | B8: Mixed date formats, impossible dates, missing values. | C8: 2023-08-14, 03/22/2023, 2023-02-30, blank cells | D8: Breaks time-series aggregations, month-over-month analysis.
A9: Text Inconsistencies | B9: Mixed casing, leading/trailing whitespace, non-standard naming. | C9: 'North' vs ' north', 'Electronics' vs 'Elec.' | D9: Splits category/region groupings into duplicate buckets.
A10: Data Type Pollution | B10: Mixed string/numeric values in numeric fields. | C10: '5 pcs' or '$250.00' in quantity/price fields | D10: Causes errors during math calculations or database loads.
A11: Anomalies & Outliers | B11: Unrealistic numbers, negative quantities or prices. | C11: Units_Sold = 9999 or -5, Unit_Price = -150.00 | D11: Distorts mean, variance, and totals significantly.
A12: Mathematical Errors | B12: Total Amount does not match Units Sold * Unit Price. | C12: Total_Amount = $1,550.50 when 5 * $210 = $1,050 | D12: Lead to incorrect financial reporting to stakeholders.
A13: Invalid / Missing Data | B13: Malformed email formats and empty cells across attributes. | C13: 'invalid_email_at_gmail.com', missing regions/payments | D13: Impacts customer reachability analysis and completeness.

Sheet Raw_Sales_Data
A1: Transaction_ID | B1: Date | C1: Region | D1: Category | E1: Units_Sold | F1: Unit_Price | G1: Total_Amount | H1: Customer_Email | I1: Payment_Method
A2: TXN-1000 | B2: 2023-07-13 | C2: South | D2: Office Supplies | E2: 5 | F2: 387.29 | G2: 1936.45 | H2: user_0@company.com | I2: cc
A3: TXN-1001 | B3: 18-Nov-2023 | C3: north | D3: Office-Supplies | E3: 4 | F3: 60.94 | G3: 243.76 | H3: user_1@company.com | I3: CREDIT CARD
A4: TXN-1002 | B4: 2023-12-27 | C4: West | D4: Office Supplies | E4: 4 | F4: 481.56 | G4: 1926.24 | H4: user_2@company.com
A5: TXN-1003 | C5: EAST | D5: electronics | E5: 5 | F5: 446.21 | G5: 2231.05 | H5: user_3@company.com | I5: PayPal
A6: TXN-1004 | B6: 2023-05-29 | C6: NORTH | D6: Elec. | E6: 5 pcs | F6: 142.47 | G6: 712.35 | H6: user_4@company.com | I6: Credit Card
A7: TXN-1005 | B7: 2023/02/21 00:00 | C7: East | D7: Office-Supplies | E7: 3 | F7: 413.15 | G7: 1239.45 | H7: user_5@company.com | I7: Paypal
A8: TXN-1006 | B8: 22-Nov-2023 | C8: EAST | D8: Furniture | E8: 5 | F8: 263.98 | G8: 1319.9 | H8: user_6@company.com | I8: Paypal
A9: TXN-1007 | B9: 07/01/2023 | C9: East | D9: Furniture | E9: 4 | F9: 236.29 | G9: 945.16 | H9: user_7@company.com | I9: Paypal
A10: TXN-1008 | B10: 2023-12-26 | C10: NORTH | D10: Office-Supplies | E10: 6 | F10: 164.07 | G10: 984.42 | H10: user_8@company.com | I10: Debit
A11: TXN-1009 | B11: 03/29/2023 | C11: West | D11: Office Supplies | E11: 7 | F11: 294.67 | G11: 2062.69 | H11: user_9@company.com | I11: Debit
A12: TXN-1010 | B12: 14-Jul-2023 | C12: North | D12: Furniture | E12: 2 | F12: 367.65 | H12: user_10@company.com | I12: cc
A13: TXN-1011 | B13: 11/24/2023 | C13: South | D13: Office-Supplies | E13: 5 | F13: 211.36 | H13: user_11@company.com
A14: TXN-1012 | B14: 01/29/2023 | C14: West | D14: Furniture | E14: 5 | F14: 318.32 | G14: 1645.25 | H14: user_12@company.com | I14: Credit Card
A15: TXN-1013 | B15: 2023/06/11 00:00 | C15: West | D15: Office-Supplies | E15: 6 | F15: 352.66 | H15: invalid_email_at_gmail.com | I15: Cash
A16: TXN-1014 | B16: 19-Apr-2023 | C16: South | D16: OFFICE SUPPLIES | E16: 4 | F16: 358.45 | G16: 1433.8 | H16: user_14@company.com | I16: cc
A17: TXN-1015 | B17: 2023/09/13 00:00 | C17: South | D17: Elec. | E17: 6 | F17: 35.46 | G17: 212.76 | H17: user_15@company.com | I17: Paypal
A18: TXN-1016 | B18: 2023/11/26 00:00 | C18: South | D18: Office Supplies | E18: 6 | F18: 431.28 | G18: 2587.68 | H18: invalid_email_at_gmail.com | I18: Debit
A19: TXN-1017 | B19: 03/13/2023 | D19: OFFICE SUPPLIES | E19: 1 | F19: 234.54 | G19: 234.54 | H19: user_17@company.com | I19: cc
A20: TXN-1018 | B20: 03-Oct-2023 | C20: North | D20: Furniture | E20: 7 | F20: 138.58 | G20: 970.06 | H20: user_18@company.com | I20: Debit
A21: TXN-1019 | B21: 2023/08/08 00:00 | C21: NORTH | D21: Furniture | E21: 2 | F21: 128.46 | G21: 623.43 | H21: user_19@company.com | I21: cc
A22: TXN-1020 | B22: 2023/03/12 00:00 | C22: north | D22: Office Supplies | E22: 11 | F22: 246.68 | G22: 2713.48 | H22: user_20@company.com | I22: Debit
A23: TXN-1021 | B23: 31/11/2023 | C23: north | D23: Office-Supplies | E23: 4 | F23: 444.55 | G23: 1778.2 | H23: user_21@company.com | I23: Paypal
A24: TXN-1022 | C24: East | D24: Elec. | E24: 9999 | F24: 195.39 | G24: 586.17 | H24: user_22@company.com | I24: cc
A25: TXN-1023 | B25: 11/18/2023 | C25: West | D25: electronics | E25: 8 | F25: 377.37 | G25: 3018.96 | H25: user_23@company.com
A26: TXN-1024 | B26: 2023-08-05 | C26: EAST | D26: Furniture | E26: 3 | F26: 57.44 | G26: 172.32 | H26: user_24@company.com | I26: Paypal
A27: TXN-1025 | B27: 2023/11/02 00:00 | D27: OFFICE SUPPLIES | E27: 3 | F27: 243.27 | G27: 729.81 | H27: user_25@company.com | I27: Debit
A28: TXN-1026 | B28: 2023-10-11 | C28: South | D28: Elec. | E28: 5 | F28: 495.93 | H28: invalid_email_at_gmail.com | I28: PayPal
A29: TXN-1027 | B29: 28-Feb-2023 | C29: West | D29: electronics | E29: 8 | F29: 387.51 | G29: 3100.08 | H29: user_27@company.com | I29: Credit Card
A30: TXN-1028 | B30: 2023-06-24 | C30: North | D30: Furniture | E30: 3 | F30: 113.16 | G30: 339.48 | H30: user_28@company.com | I30: CASH
A31: TXN-1029 | B31: 2023/03/22 00:00 | C31: EAST | D31: Office-Supplies | E31: 2 | F31: 255.71 | G31: 511.42 | H31: user_29@company.com | I31: cc
A32: TXN-1030 | C32: West | D32: Office Supplies | E32: 5 pcs | F32: 124.48 | G32: 622.4 | H32: user_at_company | I32: Debit
A33: TXN-1031 | B33: 05/15/2023 | C33: EAST | D33: Electronics | E33: 5 pcs | F33: 210.68 | G33: 632.04 | H33: user_at_company | I33: Paypal
A34: TXN-1032 | B34: 24-Feb-2023 | C34: West | D34: Elec. | E34: 8 | F34: 392.24 | G34: 3137.92 | H34: user_32@company.com | I34: Debit
A35: TXN-1033 | B35: 09/17/2023 | C35: West | D35: Office-Supplies | E35: 10 | F35: 387.9 | G35: 3879 | H35: user_33@company.com | I35: Credit Card
A36: TXN-1034 | B36: 2023-03-24 | D36: Electronics | E36: 3 | F36: 121.77 | G36: 365.31 | H36: user_34@company.com | I36: PayPal
A37: TXN-1035 | B37: 2023-09-08 | C37: South | D37: electronics | E37: 2 | F37: 461.89 | G37: 923.78 | H37: user_35@company.com | I37: CASH
A38: TXN-1036 | B38: 05-Jul-2023 | C38: West | D38: Elec. | E38: 5 | F38: 300.36 | G38: 1501.8 | H38: user_36@company.com | I38: PayPal
A39: TXN-1037 | B39: 2023-05-04 | C39: South | D39: OFFICE SUPPLIES | E39: 7 | F39: 196.16 | G39: 1373.12 | H39: user_37@company.com | I39: Debit
A40: TXN-1038 | B40: 31/11/2023 | C40: north | D40: Office-Supplies | E40: 6 | F40: 255.95 | G40: 1535.7 | H40: user_38@company.com | I40: CREDIT CARD
A41: TXN-1039 | B41: 02/05/2023 | C41: EAST | D41: electronics | E41: 6 | F41: 306.48 | G41: 1838.88 | H41: user_39@company.com | I41: Cash
A42: TXN-1040 | B42: 09/01/2023 | C42: North | D42: electronics | E42: 2 | F42: 284.35 | G42: 568.7 | H42: user_40@company.com
A43: TXN-1041 | B43: 2023/11/07 00:00 | C43: West | D43: Furniture | E43: 4 | F43: 248.34 | G43: 1050.43 | H43: user_at_company | I43: Debit
A44: TXN-1042 | B44: 10/04/2023 | D44: Furniture | E44: 9 | F44: 257.42 | H44: user_42@company.com
A45: TXN-1043 | B45: 24-Jul-2023 | C45: West | D45: Office Supplies | E45: 7 | F45: 96.44 | G45: 675.08 | H45: user_43@company.com | I45: PayPal
A46: TXN-1044 | B46: 2023/09/22 00:00 | D46: electronics | E46: 11 | F46: 408.24 | G46: 4490.64 | H46: user_44@company.com | I46: PayPal
A47: TXN-1045 | B47: 2023-04-26 | D47: Electronics | E47: 8 | F47: 275.46 | G47: 2203.68 | H47: user_45@company.com | I47: PayPal
A48: TXN-1046 | B48: 10/29/2023 | C48: NORTH | D48: Office-Supplies | E48: 3 | F48: 74.23 | G48: 561.7 | H48: user_46@company.com
A49: TXN-1047 | B49: 2023-01-04 | C49: north | D49: Office-Supplies | E49: 2 | F49: 385.42 | G49: 770.84 | H49: user_47@company.com | I49: Paypal
A50: TXN-1048 | B50: 01/31/2023 | C50: West | D50: Furniture | E50: 3 | F50: 466.9 | G50: 1400.7 | H50: user_48@company.com | I50: Cash
A51: TXN-1049 | B51: 2023-02-30 | C51: NORTH | D51: Electronics | E51: 5 pcs | F51: 474.18 | H51: user_49@company.com | I51: PayPal
A52: TXN-1050 | C52: NORTH | D52: Elec. | E52: 5 | F52: 190.82 | G52: 954.1 | H52: user_50@company.com
A53: TXN-1051 | B53: 09/21/2023 | C53: South | D53: OFFICE SUPPLIES | E53: 5 | F53: 76.4 | G53: 382 | H53: user_51@company.com
A54: TXN-1052 | B54: 09/06/2023 | C54: South | D54: OFFICE SUPPLIES | E54: 4 | F54: 264.02 | G54: 1056.08 | H54: user_52@company.com | I54: PayPal
A55: TXN-1053 | B55: 2023/10/20 00:00 | C55: NORTH | D55: Electronics | E55: 3 | F55: 65.18 | G55: 195.54 | H55: user_53@company.com | I55: Debit
A56: TXN-1054 | B56: 2023/08/31 00:00 | C56: North | D56: Furniture | E56: 8 | F56: 467.65 | G56: 3741.2 | I56: cc
A57: TXN-1055 | B57: 2023/02/19 00:00 | C57: EAST | D57: Furniture | E57: 2 | F57: 99.95 | G57: 199.9 | H57: user_55@company.com | I57: CREDIT CARD
A58: TXN-1056 | B58: 2023/07/30 00:00 | C58: north | D58: Furniture | E58: 1 | F58: 133.86 | G58: 133.86 | H58: user_56@company.com | I58: Debit
A59: TXN-1057 | B59: 2023-01-28 | C59: EAST | D59: Electronics | E59: 4 | F59: 209.25 | G59: 837 | H59: user_57@company.com | I59: Credit Card
A60: TXN-1058 | B60: 2023-02-30 | C60: South | D60: Furniture | E60: 5 | F60: 197.75 | G60: 988.75 | H60: user_58@company.com | I60: Cash
A61: TXN-1059 | B61: 02/25/2023 | C61: NORTH | D61: Elec. | E61: 4 | F61: 399.38 | G61: 1597.52 | H61: user_59@company.com
A62: TXN-1060 | B62: 2023/10/02 00:00 | D62: Electronics | E62: 3 | F62: -32.17 | G62: 700.8 | H62: user_60@company.com | I62: Debit
A63: TXN-1061 | B63: 04-Apr-2023 | C63: South | D63: Office Supplies | E63: 4 | F63: 93.68 | G63: 374.72 | H63: user_61@company.com | I63: Debit
A64: TXN-1062 | B64: 2023/02/08 00:00 | C64: East | D64: Furniture | E64: 8 | F64: 140.93 | G64: 1127.44 | H64: user_62@company.com | I64: CREDIT CARD
A65: TXN-1063 | B65: 2023-10-09 | C65: north | D65: Electronics | E65: 2 | F65: 259.47 | G65: 518.94 | H65: user_63@company.com | I65: CREDIT CARD
A66: TXN-1064 | C66: north | D66: Elec. | E66: 2 | F66: 82.25 | G66: 164.5 | H66: user_64@company.com | I66: cc
A67: TXN-1065 | B67: 2023-01-08 | C67: EAST | D67: electronics | E67: 2 | F67: 309.71 | H67: user_65@company.com | I67: CASH
A68: TXN-1066 | B68: 05/02/2023 | C68: West | D68: Furniture | E68: 7 | F68: -194.4 | G68: 2010.54 | H68: user_66@company.com | I68: PayPal
A69: TXN-1067 | B69: 09/04/2023 | C69: EAST | D69: Office-Supplies | E69: 6 | F69: 360.2 | G69: 2161.2 | H69: user_67@company.com | I69: cc
A70: TXN-1068 | B70: 01/31/2023 | C70: West | D70: Office Supplies | E70: 7 | F70: 469.48 | G70: 3286.36 | H70: user_68@company.com | I70: Debit
A71: TXN-1069 | B71: 19-Jul-2023 | C71: East | D71: Office-Supplies | E71: 6 | F71: 457 | G71: 2742 | H71: user_69@company.com | I71: Cash
A72: TXN-1070 | B72: 21-Aug-2023 | C72: South | D72: Office-Supplies | E72: 7 | F72: -41.56 | G72: 3315.06 | H72: user_70@company.com
A73: TXN-1071 | B73: 2023/10/12 00:00 | C73: West | D73: Furniture | E73: 6 | F73: 129.91 | G73: 779.46 | H73: user_71@company.com | I73: CREDIT CARD
A74: TXN-1072 | B74: 06/01/2023 | C74: West | D74: Electronics | E74: 4 | F74: 74.47 | G74: 297.88 | H74: user_72@company.com | I74: Paypal
A75: TXN-1073 | B75: 2023-10-24 | C75: North | D75: electronics | E75: 2 | F75: 158.12 | H75: user_73@company.com | I75: cc
A76: TXN-1074 | B76: 2023-01-30 | D76: electronics | E76: -7 | F76: 448.59 | G76: 1345.77 | H76: user_74@company.com | I76: Paypal
A77: TXN-1075 | B77: 09/15/2023 | D77: Furniture | E77: 4 | F77: 486.31 | G77: 1945.24 | H77: user_75@company.com | I77: Paypal
A78: TXN-1076 | C78: West | D78: Office Supplies | E78: 7 | F78: 431.07 | G78: 3017.49 | H78: user_76@company.com | I78: PayPal
A79: TXN-1077 | B79: 2023-04-06 | C79: EAST | D79: Office Supplies | E79: 4 | F79: 63.91 | G79: 255.64
A80: TXN-1078 | B80: 12/12/2023 | C80: north | D80: Furniture | E80: 3 | F80: 474.24 | G80: 1873.18 | H80: user_78@company.com | I80: PayPal
A81: TXN-1079 | B81: 10/19/2023 | C81: EAST | D81: Furniture | E81: 2 | F81: 217.45 | G81: 697.5 | H81: user_79@company.com | I81: Cash
A82: TXN-1080 | B82: 2023-01-21 | C82: NORTH | D82: Furniture | F82: 14.56 | G82: 87.36 | H82: user_80@company.com
A83: TXN-1081 | B83: 26-Oct-2023 | C83: NORTH | D83: OFFICE SUPPLIES | E83: 3 | F83: 226.77 | G83: 680.31 | H83: user_81@company.com | I83: Debit
A84: TXN-1082 | B84: 15-Apr-2023 | D84: Office-Supplies | E84: 5 | F84: 32.57 | H84: user_82@company.com | I84: cc
A85: TXN-1083 | B85: 07/22/2023 | D85: Electronics | E85: 9 | F85: 276.5 | G85: 2488.5 | H85: user_83@company.com | I85: PayPal
A86: TXN-1084 | B86: 2023/06/03 00:00 | D86: Furniture | E86: 6 | F86: 175.89 | G86: 1055.34 | H86: user_84@company.com | I86: Paypal
A87: TXN-1085 | B87: 2023-02-07 | C87: north | D87: Elec. | E87: 6 | F87: 241.98 | G87: 1656.48 | H87: invalid_email_at_gmail.com | I87: CREDIT CARD
A88: TXN-1086 | B88: 2023-10-16 | C88: north | D88: Office-Supplies | E88: 9 | F88: 310.45 | G88: 2794.05 | H88: user_86@company.com | I88: Cash
A89: TXN-1087 | B89: 2023-02-30 | D89: electronics | E89: 4 | F89: 435.71 | G89: 1742.84 | H89: user_87@company.com | I89: CREDIT CARD
A90: TXN-1088 | B90: 05/16/2023 | C90: north | D90: electronics | E90: 9 | F90: 334.33 | G90: 3008.97 | H90: user_88@company.com | I90: Paypal
A91: TXN-1089 | B91: 02/05/2023 | C91: South | D91: Furniture | E91: 2 | F91: 222.68 | G91: 445.36 | H91: user_89@company.com | I91: CASH
A92: TXN-1090 | B92: 2023/03/22 00:00 | C92: West | D92: Office Supplies | E92: 10 | F92: 411.52 | G92: 4115.2 | H92: user_90@company.com | I92: CREDIT CARD
A93: TXN-1091 | B93: 27-Dec-2023 | C93: East | D93: electronics | E93: 6 | F93: 453.74 | G93: 2722.44 | H93: user_91@company.com | I93: CREDIT CARD
A94: TXN-1092 | B94: 2023-12-01 | C94: EAST | D94: Furniture | E94: 9 | F94: 68.68 | G94: 618.12 | H94: invalid_email_at_gmail.com | I94: CREDIT CARD
A95: TXN-1093 | B95: 11-Oct-2023 | C95: South | D95: Furniture | E95: 4 | F95: 270.65 | H95: user_93@company.com | I95: Cash
A96: TXN-1094 | B96: 02/23/2023 | C96: EAST | D96: OFFICE SUPPLIES | E96: -5 | F96: 149.41 | G96: 149.41 | H96: user_94@company.com
A97: TXN-1095 | B97: 02/24/2023 | C97: West | D97: Office-Supplies | E97: 6 | F97: 33.06 | H97: user_95@company.com | I97: Debit
A98: TXN-1096 | B98: 11/06/2023 | D98: OFFICE SUPPLIES | F98: 337.59 | G98: 2700.72 | H98: user_96@company.com | I98: CASH
A99: TXN-1097 | B99: 15-Apr-2023 | D99: Furniture | E99: 6 | F99: 432.76 | G99: 2596.56 | H99: user_97@company.com | I99: PayPal
A100: TXN-1098 | B100: 2023-05-09 | C100: West | D100: Office Supplies | E100: 2 | F100: 89.82 | H100: user_98@company.com | I100: Paypal
...

Sheet messy_sales_dataset
A1: Transaction_ID | B1: Date | C1: Region | D1: Category | E1: Units_Sold | F1: Unit_Price | G1: Total_Amount | H1: Customer_Email | I1: Payment_Method
A2: TXN-1000 | B2: 2023-07-13 | C2: =PROPER(Raw_Sales_Data!C2) -> South | D2: Office Supplies | E2: 5 | F2: 387.29 | G2: 1936.45 | H2: user_0@company.com | I2: cc
A3: TXN-1001 | B3: 18-Nov-2023 | C3: =PROPER(Raw_Sales_Data!C3) -> North | D3: Office Supplies | E3: 4 | F3: 60.94 | G3: 243.76 | H3: user_1@company.com | I3: CREDIT CARD
A4: TXN-1002 | B4: 2023-12-27 | C4: =PROPER(Raw_Sales_Data!C4) -> West | D4: Office Supplies | E4: 4 | F4: 481.56 | G4: 1926.24 | H4: user_2@company.com
A5: TXN-1003 | C5: =PROPER(Raw_Sales_Data!C5) -> East | D5: Electronics | E5: 5 | F5: 446.21 | G5: 2231.05 | H5: user_3@company.com | I5: PayPal
A6: TXN-1004 | B6: 2023-05-29 | C6: =PROPER(Raw_Sales_Data!C6) -> North | D6: Electronics | E6: 5 | F6: 142.47 | G6: 712.35 | H6: user_4@company.com | I6: Credit Card
A7: TXN-1005 | B7: 2023/02/21 00:00 | C7: =PROPER(Raw_Sales_Data!C7) -> East | D7: Office Supplies | E7: 3 | F7: 413.15 | G7: 1239.45 | H7: user_5@company.com | I7: Paypal
A8: TXN-1006 | B8: 22-Nov-2023 | C8: =PROPER(Raw_Sales_Data!C8) -> East | D8: Furniture | E8: 5 | F8: 263.98 | G8: 1319.9 | H8: user_6@company.com | I8: Paypal
A9: TXN-1007 | B9: 07/01/2023 | C9: =PROPER(Raw_Sales_Data!C9) -> East | D9: Furniture | E9: 4 | F9: 236.29 | G9: 945.16 | H9: user_7@company.com | I9: Paypal
A10: TXN-1008 | B10: 2023-12-26 | C10: =PROPER(Raw_Sales_Data!C10) -> North | D10: Office Supplies | E10: 6 | F10: 164.07 | G10: 984.42 | H10: user_8@company.com | I10: Debit
A11: TXN-1009 | B11: 03/29/2023 | C11: =PROPER(Raw_Sales_Data!C11) -> West | D11: Office Supplies | E11: 7 | F11: 294.67 | G11: 2062.69 | H11: user_9@company.com | I11: Debit
A12: TXN-1010 | B12: 14-Jul-2023 | C12: =PROPER(Raw_Sales_Data!C12) -> North | D12: Furniture | E12: 2 | F12: 367.65 | H12: user_10@company.com | I12: cc
A13: TXN-1011 | B13: 11/24/2023 | C13: =PROPER(Raw_Sales_Data!C13) -> South | D13: Office Supplies | E13: 5 | F13: 211.36 | H13: user_11@company.com
A14: TXN-1012 | B14: 01/29/2023 | C14: =PROPER(Raw_Sales_Data!C14) -> West | D14: Furniture | E14: 5 | F14: 318.32 | G14: 1645.25 | H14: user_12@company.com | I14: Credit Card
A15: TXN-1013 | B15: 2023/06/11 00:00 | C15: =PROPER(Raw_Sales_Data!C15) -> West | D15: Office Supplies | E15: 6 | F15: 352.66 | H15: invalid_email_at_gmail.com | I15: Cash
A16: TXN-1014 | B16: 19-Apr-2023 | C16: =PROPER(Raw_Sales_Data!C16) -> South | D16: Office Supplies | E16: 4 | F16: 358.45 | G16: 1433.8 | H16: user_14@company.com | I16: cc
A17: TXN-1015 | B17: 2023/09/13 00:00 | C17: =PROPER(Raw_Sales_Data!C17) -> South | D17: Electronics | E17: 6 | F17: 35.46 | G17: 212.76 | H17: user_15@company.com | I17: Paypal
A18: TXN-1016 | B18: 2023/11/26 00:00 | C18: =PROPER(Raw_Sales_Data!C18) -> South | D18: Office Supplies | E18: 6 | F18: 431.28 | G18: 2587.68 | H18: invalid_email_at_gmail.com | I18: Debit
A19: TXN-1017 | B19: 03/13/2023 | C19: =PROPER(Raw_Sales_Data!C19) | D19: Office Supplies | E19: 1 | F19: 234.54 | G19: 234.54 | H19: user_17@company.com | I19: cc
A20: TXN-1018 | B20: 03-Oct-2023 | C20: =PROPER(Raw_Sales_Data!C20) -> North | D20: Furniture | E20: 7 | F20: 138.58 | G20: 970.06 | H20: user_18@company.com | I20: Debit
A21: TXN-1019 | B21: 2023/08/08 00:00 | C21: =PROPER(Raw_Sales_Data!C21) -> North | D21: Furniture | E21: 2 | F21: 128.46 | G21: 623.43 | H21: user_19@company.com | I21: cc
A22: TXN-1020 | B22: 2023/03/12 00:00 | C22: =PROPER(Raw_Sales_Data!C22) -> North | D22: Office Supplies | E22: 11 | F22: 246.68 | G22: 2713.48 | H22: user_20@company.com | I22: Debit
A23: TXN-1021 | B23: 31/11/2023 | C23: =PROPER(Raw_Sales_Data!C23) -> North | D23: Office Supplies | E23: 4 | F23: 444.55 | G23: 1778.2 | H23: user_21@company.com | I23: Paypal
A24: TXN-1022 | C24: =PROPER(Raw_Sales_Data!C24) -> East | D24: Electronics | E24: 9999 | F24: 195.39 | G24: 586.17 | H24: user_22@company.com | I24: cc
A25: TXN-1023 | B25: 11/18/2023 | C25: =PROPER(Raw_Sales_Data!C25) -> West | D25: Electronics | E25: 8 | F25: 377.37 | G25: 3018.96 | H25: user_23@company.com
A26: TXN-1024 | B26: 2023-08-05 | C26: =PROPER(Raw_Sales_Data!C26) -> East | D26: Furniture | E26: 3 | F26: 57.44 | G26: 172.32 | H26: user_24@company.com | I26: Paypal
A27: TXN-1025 | B27: 2023/11/02 00:00 | C27: =PROPER(Raw_Sales_Data!C27) | D27: Office Supplies | E27: 3 | F27: 243.27 | G27: 729.81 | H27: user_25@company.com | I27: Debit
A28: TXN-1026 | B28: 2023-10-11 | C28: =PROPER(Raw_Sales_Data!C28) -> South | D28: Electronics | E28: 5 | F28: 495.93 | H28: invalid_email_at_gmail.com | I28: PayPal
A29: TXN-1027 | B29: 28-Feb-2023 | C29: =PROPER(Raw_Sales_Data!C29) -> West | D29: Electronics | E29: 8 | F29: 387.51 | G29: 3100.08 | H29: user_27@company.com | I29: Credit Card
A30: TXN-1028 | B30: 2023-06-24 | C30: =PROPER(Raw_Sales_Data!C30) -> North | D30: Furniture | E30: 3 | F30: 113.16 | G30: 339.48 | H30: user_28@company.com | I30: CASH
A31: TXN-1029 | B31: 2023/03/22 00:00 | C31: =PROPER(Raw_Sales_Data!C31) -> East | D31: Office Supplies | E31: 2 | F31: 255.71 | G31: 511.42 | H31: user_29@company.com | I31: cc
A32: TXN-1030 | C32: =PROPER(Raw_Sales_Data!C32) -> West | D32: Office Supplies | E32: 5 | F32: 124.48 | G32: 622.4 | H32: user_at_company | I32: Debit
A33: TXN-1031 | B33: 05/15/2023 | C33: =PROPER(Raw_Sales_Data!C33) -> East | D33: Electronics | E33: 5 | F33: 210.68 | G33: 632.04 | H33: user_at_company | I33: Paypal
A34: TXN-1032 | B34: 24-Feb-2023 | C34: =PROPER(Raw_Sales_Data!C34) -> West | D34: Electronics | E34: 8 | F34: 392.24 | G34: 3137.92 | H34: user_32@company.com | I34: Debit
A35: TXN-1033 | B35: 09/17/2023 | C35: =PROPER(Raw_Sales_Data!C35) -> West | D35: Office Supplies | E35: 10 | F35: 387.9 | G35: 3879 | H35: user_33@company.com | I35: Credit Card
A36: TXN-1034 | B36: 2023-03-24 | C36: =PROPER(Raw_Sales_Data!C36) | D36: Electronics | E36: 3 | F36: 121.77 | G36: 365.31 | H36: user_34@company.com | I36: PayPal
A37: TXN-1035 | B37: 2023-09-08 | C37: =PROPER(Raw_Sales_Data!C37) -> South | D37: Electronics | E37: 2 | F37: 461.89 | G37: 923.78 | H37: user_35@company.com | I37: CASH
A38: TXN-1036 | B38: 05-Jul-2023 | C38: =PROPER(Raw_Sales_Data!C38) -> West | D38: Electronics | E38: 5 | F38: 300.36 | G38: 1501.8 | H38: user_36@company.com | I38: PayPal
A39: TXN-1037 | B39: 2023-05-04 | C39: =PROPER(Raw_Sales_Data!C39) -> South | D39: Office Supplies | E39: 7 | F39: 196.16 | G39: 1373.12 | H39: user_37@company.com | I39: Debit
A40: TXN-1038 | B40: 31/11/2023 | C40: =PROPER(Raw_Sales_Data!C40) -> North | D40: Office Supplies | E40: 6 | F40: 255.95 | G40: 1535.7 | H40: user_38@company.com | I40: CREDIT CARD
A41: TXN-1039 | B41: 02/05/2023 | C41: =PROPER(Raw_Sales_Data!C41) -> East | D41: Electronics | E41: 6 | F41: 306.48 | G41: 1838.88 | H41: user_39@company.com | I41: Cash
A42: TXN-1040 | B42: 09/01/2023 | C42: =PROPER(Raw_Sales_Data!C42) -> North | D42: Electronics | E42: 2 | F42: 284.35 | G42: 568.7 | H42: user_40@company.com
A43: TXN-1041 | B43: 2023/11/07 00:00 | C43: =PROPER(Raw_Sales_Data!C43) -> West | D43: Furniture | E43: 4 | F43: 248.34 | G43: 1050.43 | H43: user_at_company | I43: Debit
A44: TXN-1042 | B44: 10/04/2023 | C44: =PROPER(Raw_Sales_Data!C44) | D44: Furniture | E44: 9 | F44: 257.42 | H44: user_42@company.com
A45: TXN-1043 | B45: 24-Jul-2023 | C45: =PROPER(Raw_Sales_Data!C45) -> West | D45: Office Supplies | E45: 7 | F45: 96.44 | G45: 675.08 | H45: user_43@company.com | I45: PayPal
A46: TXN-1044 | B46: 2023/09/22 00:00 | C46: =PROPER(Raw_Sales_Data!C46) | D46: Electronics | E46: 11 | F46: 408.24 | G46: 4490.64 | H46: user_44@company.com | I46: PayPal
A47: TXN-1045 | B47: 2023-04-26 | C47: =PROPER(Raw_Sales_Data!C47) | D47: Electronics | E47: 8 | F47: 275.46 | G47: 2203.68 | H47: user_45@company.com | I47: PayPal
A48: TXN-1046 | B48: 10/29/2023 | C48: =PROPER(Raw_Sales_Data!C48) -> North | D48: Office Supplies | E48: 3 | F48: 74.23 | G48: 561.7 | H48: user_46@company.com
A49: TXN-1047 | B49: 2023-01-04 | C49: =PROPER(Raw_Sales_Data!C49) -> North | D49: Office Supplies | E49: 2 | F49: 385.42 | G49: 770.84 | H49: user_47@company.com | I49: Paypal
A50: TXN-1048 | B50: 01/31/2023 | C50: =PROPER(Raw_Sales_Data!C50) -> West | D50: Furniture | E50: 3 | F50: 466.9 | G50: 1400.7 | H50: user_48@company.com | I50: Cash
A51: TXN-1049 | B51: 2023-02-30 | C51: =PROPER(Raw_Sales_Data!C51) -> North | D51: Electronics | E51: 5 | F51: 474.18 | H51: user_49@company.com | I51: PayPal
A52: TXN-1050 | C52: =PROPER(Raw_Sales_Data!C52) -> North | D52: Electronics | E52: 5 | F52: 190.82 | G52: 954.1 | H52: user_50@company.com
A53: TXN-1051 | B53: 09/21/2023 | C53: =PROPER(Raw_Sales_Data!C53) -> South | D53: Office Supplies | E53: 5 | F53: 76.4 | G53: 382 | H53: user_51@company.com
A54: TXN-1052 | B54: 09/06/2023 | C54: =PROPER(Raw_Sales_Data!C54) -> South | D54: Office Supplies | E54: 4 | F54: 264.02 | G54: 1056.08 | H54: user_52@company.com | I54: PayPal
A55: TXN-1053 | B55: 2023/10/20 00:00 | C55: =PROPER(Raw_Sales_Data!C55) -> North | D55: Electronics | E55: 3 | F55: 65.18 | G55: 195.54 | H55: user_53@company.com | I55: Debit
A56: TXN-1054 | B56: 2023/08/31 00:00 | C56: =PROPER(Raw_Sales_Data!C56) -> North | D56: Furniture | E56: 8 | F56: 467.65 | G56: 3741.2 | I56: cc
A57: TXN-1055 | B57: 2023/02/19 00:00 | C57: =PROPER(Raw_Sales_Data!C57) -> East | D57: Furniture | E57: 2 | F57: 99.95 | G57: 199.9 | H57: user_55@company.com | I57: CREDIT CARD
A58: TXN-1056 | B58: 2023/07/30 00:00 | C58: =PROPER(Raw_Sales_Data!C58) -> North | D58: Furniture | E58: 1 | F58: 133.86 | G58: 133.86 | H58: user_56@company.com | I58: Debit
A59: TXN-1057 | B59: 2023-01-28 | C59: =PROPER(Raw_Sales_Data!C59) -> East | D59: Electronics | E59: 4 | F59: 209.25 | G59: 837 | H59: user_57@company.com | I59: Credit Card
A60: TXN-1058 | B60: 2023-02-30 | C60: =PROPER(Raw_Sales_Data!C60) -> South | D60: Furniture | E60: 5 | F60: 197.75 | G60: 988.75 | H60: user_58@company.com | I60: Cash
A61: TXN-1059 | B61: 02/25/2023 | C61: =PROPER(Raw_Sales_Data!C61) -> North | D61: Electronics | E61: 4 | F61: 399.38 | G61: 1597.52 | H61: user_59@company.com
A62: TXN-1060 | B62: 2023/10/02 00:00 | C62: =PROPER(Raw_Sales_Data!C62) | D62: Electronics | E62: 3 | F62: -32.17 | G62: 700.8 | H62: user_60@company.com | I62: Debit
A63: TXN-1061 | B63: 04-Apr-2023 | C63: =PROPER(Raw_Sales_Data!C63) -> South | D63: Office Supplies | E63: 4 | F63: 93.68 | G63: 374.72 | H63: user_61@company.com | I63: Debit
A64: TXN-1062 | B64: 2023/02/08 00:00 | C64: =PROPER(Raw_Sales_Data!C64) -> East | D64: Furniture | E64: 8 | F64: 140.93 | G64: 1127.44 | H64: user_62@company.com | I64: CREDIT CARD
A65: TXN-1063 | B65: 2023-10-09 | C65: =PROPER(Raw_Sales_Data!C65) -> North | D65: Electronics | E65: 2 | F65: 259.47 | G65: 518.94 | H65: user_63@company.com | I65: CREDIT CARD
A66: TXN-1064 | C66: =PROPER(Raw_Sales_Data!C66) -> North | D66: Electronics | E66: 2 | F66: 82.25 | G66: 164.5 | H66: user_64@company.com | I66: cc
A67: TXN-1065 | B67: 2023-01-08 | C67: =PROPER(Raw_Sales_Data!C67) -> East | D67: Electronics | E67: 2 | F67: 309.71 | H67: user_65@company.com | I67: CASH
A68: TXN-1066 | B68: 05/02/2023 | C68: =PROPER(Raw_Sales_Data!C68) -> West | D68: Furniture | E68: 7 | F68: -194.4 | G68: 2010.54 | H68: user_66@company.com | I68: PayPal
A69: TXN-1067 | B69: 09/04/2023 | C69: =PROPER(Raw_Sales_Data!C69) -> East | D69: Office Supplies | E69: 6 | F69: 360.2 | G69: 2161.2 | H69: user_67@company.com | I69: cc
A70: TXN-1068 | B70: 01/31/2023 | C70: =PROPER(Raw_Sales_Data!C70) -> West | D70: Office Supplies | E70: 7 | F70: 469.48 | G70: 3286.36 | H70: user_68@company.com | I70: Debit
A71: TXN-1069 | B71: 19-Jul-2023 | C71: =PROPER(Raw_Sales_Data!C71) -> East | D71: Office Supplies | E71: 6 | F71: 457 | G71: 2742 | H71: user_69@company.com | I71: Cash
A72: TXN-1070 | B72: 21-Aug-2023 | C72: =PROPER(Raw_Sales_Data!C72) -> South | D72: Office Supplies | E72: 7 | F72: -41.56 | G72: 3315.06 | H72: user_70@company.com
A73: TXN-1071 | B73: 2023/10/12 00:00 | C73: =PROPER(Raw_Sales_Data!C73) -> West | D73: Furniture | E73: 6 | F73: 129.91 | G73: 779.46 | H73: user_71@company.com | I73: CREDIT CARD
A74: TXN-1072 | B74: 06/01/2023 | C74: =PROPER(Raw_Sales_Data!C74) -> West | D74: Electronics | E74: 4 | F74: 74.47 | G74: 297.88 | H74: user_72@company.com | I74: Paypal
A75: TXN-1073 | B75: 2023-10-24 | C75: =PROPER(Raw_Sales_Data!C75) -> North | D75: Electronics | E75: 2 | F75: 158.12 | H75: user_73@company.com | I75: cc
A76: TXN-1074 | B76: 2023-01-30 | C76: =PROPER(Raw_Sales_Data!C76) | D76: Electronics | E76: -7 | F76: 448.59 | G76: 1345.77 | H76: user_74@company.com | I76: Paypal
A77: TXN-1075 | B77: 09/15/2023 | C77: =PROPER(Raw_Sales_Data!C77) | D77: Furniture | E77: 4 | F77: 486.31 | G77: 1945.24 | H77: user_75@company.com | I77: Paypal
A78: TXN-1076 | C78: =PROPER(Raw_Sales_Data!C78) -> West | D78: Office Supplies | E78: 7 | F78: 431.07 | G78: 3017.49 | H78: user_76@company.com | I78: PayPal
A79: TXN-1077 | B79: 2023-04-06 | C79: =PROPER(Raw_Sales_Data!C79) -> East | D79: Office Supplies | E79: 4 | F79: 63.91 | G79: 255.64
A80: TXN-1078 | B80: 12/12/2023 | C80: =PROPER(Raw_Sales_Data!C80) -> North | D80: Furniture | E80: 3 | F80: 474.24 | G80: 1873.18 | H80: user_78@company.com | I80: PayPal
A81: TXN-1079 | B81: 10/19/2023 | C81: =PROPER(Raw_Sales_Data!C81) -> East | D81: Furniture | E81: 2 | F81: 217.45 | G81: 697.5 | H81: user_79@company.com | I81: Cash
A82: TXN-1080 | B82: 2023-01-21 | C82: =PROPER(Raw_Sales_Data!C82) -> North | D82: Furniture | F82: 14.56 | G82: 87.36 | H82: user_80@company.com
A83: TXN-1081 | B83: 26-Oct-2023 | C83: =PROPER(Raw_Sales_Data!C83) -> North | D83: Office Supplies | E83: 3 | F83: 226.77 | G83: 680.31 | H83: user_81@company.com | I83: Debit
A84: TXN-1082 | B84: 15-Apr-2023 | C84: =PROPER(Raw_Sales_Data!C84) | D84: Office Supplies | E84: 5 | F84: 32.57 | H84: user_82@company.com | I84: cc
A85: TXN-1083 | B85: 07/22/2023 | C85: =PROPER(Raw_Sales_Data!C85) | D85: Electronics | E85: 9 | F85: 276.5 | G85: 2488.5 | H85: user_83@company.com | I85: PayPal
A86: TXN-1084 | B86: 2023/06/03 00:00 | C86: =PROPER(Raw_Sales_Data!C86) | D86: Furniture | E86: 6 | F86: 175.89 | G86: 1055.34 | H86: user_84@company.com | I86: Paypal
A87: TXN-1085 | B87: 2023-02-07 | C87: =PROPER(Raw_Sales_Data!C87) -> North | D87: Electronics | E87: 6 | F87: 241.98 | G87: 1656.48 | H87: invalid_email_at_gmail.com | I87: CREDIT CARD
A88: TXN-1086 | B88: 2023-10-16 | C88: =PROPER(Raw_Sales_Data!C88) -> North | D88: Office Supplies | E88: 9 | F88: 310.45 | G88: 2794.05 | H88: user_86@company.com | I88: Cash
A89: TXN-1087 | B89: 2023-02-30 | C89: =PROPER(Raw_Sales_Data!C89) | D89: Electronics | E89: 4 | F89: 435.71 | G89: 1742.84 | H89: user_87@company.com | I89: CREDIT CARD
A90: TXN-1088 | B90: 05/16/2023 | C90: =PROPER(Raw_Sales_Data!C90) -> North | D90: Electronics | E90: 9 | F90: 334.33 | G90: 3008.97 | H90: user_88@company.com | I90: Paypal
A91: TXN-1089 | B91: 02/05/2023 | C91: =PROPER(Raw_Sales_Data!C91) -> South | D91: Furniture | E91: 2 | F91: 222.68 | G91: 445.36 | H91: user_89@company.com | I91: CASH
A92: TXN-1090 | B92: 2023/03/22 00:00 | C92: =PROPER(Raw_Sales_Data!C92) -> West | D92: Office Supplies | E92: 10 | F92: 411.52 | G92: 4115.2 | H92: user_90@company.com | I92: CREDIT CARD
A93: TXN-1091 | B93: 27-Dec-2023 | C93: =PROPER(Raw_Sales_Data!C93) -> East | D93: Electronics | E93: 6 | F93: 453.74 | G93: 2722.44 | H93: user_91@company.com | I93: CREDIT CARD
A94: TXN-1092 | B94: 2023-12-01 | C94: =PROPER(Raw_Sales_Data!C94) -> East | D94: Furniture | E94: 9 | F94: 68.68 | G94: 618.12 | H94: invalid_email_at_gmail.com | I94: CREDIT CARD
A95: TXN-1093 | B95: 11-Oct-2023 | C95: =PROPER(Raw_Sales_Data!C95) -> South | D95: Furniture | E95: 4 | F95: 270.65 | H95: user_93@company.com | I95: Cash
A96: TXN-1094 | B96: 02/23/2023 | C96: =PROPER(Raw_Sales_Data!C96) -> East | D96: Office Supplies | E96: -5 | F96: 149.41 | G96: 149.41 | H96: user_94@company.com
A97: TXN-1095 | B97: 02/24/2023 | C97: =PROPER(Raw_Sales_Data!C97) -> West | D97: Office Supplies | E97: 6 | F97: 33.06 | H97: user_95@company.com | I97: Debit
A98: TXN-1096 | B98: 11/06/2023 | C98: =PROPER(Raw_Sales_Data!C98) | D98: Office Supplies | F98: 337.59 | G98: 2700.72 | H98: user_96@company.com | I98: CASH
A99: TXN-1097 | B99: 15-Apr-2023 | C99: =PROPER(Raw_Sales_Data!C99) | D99: Furniture | E99: 6 | F99: 432.76 | G99: 2596.56 | H99: user_97@company.com | I99: PayPal
A100: TXN-1098 | B100: 2023-05-09 | C100: =PROPER(Raw_Sales_Data!C100) -> West | D100: Office Supplies | E100: 2 | F100: 89.82 | H100: user_98@company.com | I100: Paypal
...
